aliasfile/__init__.py
aliasfile/ast.py
aliasfile/cli.py
aliasfile/core.py
aliasfile/parse.py
aliasfile/runner.py
aliasfile/utils.py
aliasfile-0.1.1.dist-info/DESCRIPTION.rst
aliasfile-0.1.1.dist-info/METADATA
aliasfile-0.1.1.dist-info/RECORD
aliasfile-0.1.1.dist-info/WHEEL
aliasfile-0.1.1.dist-info/entry_points.txt
aliasfile-0.1.1.dist-info/metadata.json
aliasfile-0.1.1.dist-info/top_level.txt
tests/__init__.py
tests/test_cli.py
tests/test_core.py
tests/test_parse.py
tests/test_runner.py
tests/test_utils.py
