Metadata-Version: 2.0
Name: aliasfile
Version: 0.1.1
Summary: UNKNOWN
Home-page: https://github.com/rshk/aliasfile
Author: Samuele Santi
Author-email: UNKNOWN
License: BSD License
Platform: UNKNOWN
Classifier: License :: OSI Approved :: BSD License
Classifier: Development Status :: 1 - Planning
Classifier: Programming Language :: Python :: 3.4
Classifier: Programming Language :: Python :: 3.5
Requires-Dist: click
Requires-Dist: pyyaml
